projects/vlsi-hardware-arbiters/Archive/arb.v
module arb (
    input  wire       clk,
    input  wire       rst_n, // active low and asynchronous
    input  wire [2:0] req,
    output reg  [2:0] gnt
);

    parameter RST = 3'b000;
    parameter S_0 = 3'b001;
    parameter S_1 = 3'b010;
    parameter S_2 = 3'b100;

    reg [2:0] state, next_state;

    // State transition
    always @(posedge clk or negedge rst_n) begin
        if (!rst_n) begin
            state <= RST;
        end else begin
            state <= next_state;
        end
    end

    // Next state logic
    always @(*) begin
        case (state)
            RST: begin
                if (req[0])      next_state = S_0;
                else if (req[1]) next_state = S_1;
                else if (req[2]) next_state = S_2;
                else             next_state = RST;
            end
            S_0: begin
                if (req[1])      next_state = S_1;
                else if (req[2]) next_state = S_2;
                else if (req[0]) next_state = S_0;
                else             next_state = RST;
            end
            S_1: begin
                if (req[2])      next_state = S_2;
                else if (req[0]) next_state = S_0;
                else if (req[1]) next_state = S_1;
                else             next_state = RST;
            end
            S_2: begin
                if (req[0])      next_state = S_0;
                else if (req[1]) next_state = S_1;
                else if (req[2]) next_state = S_2;
                else             next_state = RST;
            end
            default: next_state = RST;
        endcase
    end

    // Output logic
    always @(*) begin
        gnt = state;
    end

endmodule

projects/vlsi-hardware-arbiters/arb_tb.v
`timescale 1ns/1ps

module arb_tb;

    reg clk;
    reg rst_n;
    reg [2:0] req;
    wire [2:0] gnt;

    // Instantiate the arbiter
    arb uut (
        .clk(clk),
        .rst_n(rst_n),
        .req(req),
        .gnt(gnt)
    );

    // Clock generation
    initial begin
        clk = 0;
        forever #5 clk = ~clk;
    end

    // Function or string for state name
    reg [23:0] state_name;
    always @(*) begin
        case (uut.state)
            3'b000: state_name = "RST";
            3'b001: state_name = "S_0";
            3'b010: state_name = "S_1";
            3'b100: state_name = "S_2";
            default: state_name = "INV";
        endcase
    end

    // Stimulus
    initial begin
        $dumpfile("arb.vcd");
        $dumpvars(0, arb_tb);

        // Initialize inputs
        rst_n = 0;
        req = 3'b000;
        
        // Wait for a few clock cycles before releasing reset
        #12;
        rst_n = 1;

        // Apply specified combinations of requests
        @(negedge clk) req = 3'b000;
        @(negedge clk) req = 3'b001;
        @(negedge clk) req = 3'b010;
        @(negedge clk) req = 3'b100;
        @(negedge clk) req = 3'b111;
        @(negedge clk) req = 3'b110;
        @(negedge clk) req = 3'b100;
        @(negedge clk) req = 3'b000;
        @(negedge clk) req = 3'b111;
        
        // Let it run for a few more cycles to observe behavior
        @(negedge clk);
        @(negedge clk);
        @(negedge clk);
        
        $finish;
    end

    // Clear printouts of grants at each clock cycle
    always @(posedge clk) begin
        // delay by a small amount to allow state and gnt to update
        #1;
        $display("Time=%0t | req=%b | gnt=%b | state=%s", $time, req, gnt, state_name);
    end

endmodule

projects/vlsi-hardware-arbiters/arb.vcd
$date
	Wed Jun 10 01:49:46 2026
$end
$version
	Icarus Verilog
$end
$timescale
	1ps
$end
$scope module arb_tb $end
$var wire 3 ! gnt [2:0] $end
$var reg 1 " clk $end
$var reg 3 # req [2:0] $end
$var reg 1 $ rst_n $end
$var reg 24 % state_name [23:0] $end
$scope module uut $end
$var wire 1 " clk $end
$var wire 3 & req [2:0] $end
$var wire 1 $ rst_n $end
$var parameter 3 ' RST $end
$var parameter 3 ( S_0 $end
$var parameter 3 ) S_1 $end
$var parameter 3 * S_2 $end
$var reg 3 + gnt [2:0] $end
$var reg 3 , next_state [2:0] $end
$var reg 3 - state [2:0] $end
$upscope $end
$upscope $end
$enddefinitions $end
$comment Show the parameter values. $end
$dumpall
b100 *
b10 )
b1 (
b0 '
$end
#0
$dumpvars
b0 -
b0 ,
b0 +
b0 &
b10100100101001101010100 %
0$
b0 #
0"
b0 !
$end
#5000
1"
#10000
0"
#12000
1$
#15000
1"
#20000
0"
#25000
1"
#30000
b1 ,
b1 #
b1 &
0"
#35000
b1 !
b1 +
b10100110101111100110000 %
b1 -
1"
#40000
b10 ,
b10 #
b10 &
0"
#45000
b10100110101111100110001 %
b10 !
b10 +
b10 -
1"
#50000
b100 ,
b100 #
b100 &
0"
#55000
b100 !
b100 +
b10100110101111100110010 %
b100 -
1"
#60000
b1 ,
b111 #
b111 &
0"
#65000
b10100110101111100110000 %
b1 !
b1 +
b10 ,
b1 -
1"
#70000
b110 #
b110 &
0"
#75000
b10 !
b10 +
b10100110101111100110001 %
b100 ,
b10 -
1"
#80000
b100 #
b100 &
0"
#85000
b10100110101111100110010 %
b100 !
b100 +
b100 -
1"
#90000
b0 ,
b0 #
b0 &
0"
#95000
b0 !
b0 +
b10100100101001101010100 %
b0 -
1"
#100000
b1 ,
b111 #
b111 &
0"
#105000
b10100110101111100110000 %
b1 !
b1 +
b10 ,
b1 -
1"
#110000
0"
#115000
b10 !
b10 +
b10100110101111100110001 %
b100 ,
b10 -
1"
#120000
0"
#125000
b10100110101111100110010 %
b100 !
b100 +
b1 ,
b100 -
1"
