projects/vlsi-hardware-arbiters/part2.v
module rising_edge_det (
    input wire clk,
    input wire button,
    output wire pulse
);
    reg button_d, button_dd;
    always @(posedge clk) begin
        button_d <= button;
        button_dd <= button_d;
    end
    assign pulse = button_d & ~button_dd;
endmodule

module falling_edge_det (
    input wire clk,
    input wire button,
    output wire pulse
);
    reg button_d, button_dd;
    always @(posedge clk) begin
        button_d <= button;
        button_dd <= button_d;
    end
    assign pulse = ~button_d & button_dd;
endmodule

module fsm_w (
    input wire clk,
    input wire rst_n,
    input wire w,
    output reg z
);
    parameter S0 = 2'b00, S1 = 2'b01, S2 = 2'b10;
    reg [1:0] state, next_state;
    always @(posedge clk or negedge rst_n) begin
        if (!rst_n) state <= S0;
        else state <= next_state;
    end
    always @(*) begin
        case (state)
            S0: next_state = w ? S1 : S0;
            S1: next_state = w ? S2 : S0;
            S2: next_state = w ? S2 : S0;
            default: next_state = S0;
        endcase
    end
    always @(*) z = (state == S2);
endmodule

module fsm_wx (
    input wire clk,
    input wire rst_n,
    input wire w,
    input wire x,
    output reg z
);
    parameter S0 = 2'b00, S1 = 2'b01, S2 = 2'b10, S3 = 2'b11;
    reg [1:0] state, next_state;
    wire diff = (w != x);
    always @(posedge clk or negedge rst_n) begin
        if (!rst_n) state <= S0;
        else state <= next_state;
    end
    always @(*) begin
        case (state)
            S0: next_state = diff ? S1 : S0;
            S1: next_state = diff ? S2 : S0;
            S2: next_state = diff ? S3 : S0;
            S3: next_state = diff ? S3 : S0;
            default: next_state = S0;
        endcase
    end
    always @(*) z = (state == S3);
endmodule

module fsm_1101 (
    input wire clk,
    input wire rst_n,
    input wire w,
    output reg z
);
    parameter S0 = 3'd0, S1 = 3'd1, S2 = 3'd2, S3 = 3'd3, S4 = 3'd4;
    reg [2:0] state, next_state;
    always @(posedge clk or negedge rst_n) begin
        if (!rst_n) state <= S0;
        else state <= next_state;
    end
    always @(*) begin
        case (state)
            S0: next_state = w ? S1 : S0;
            S1: next_state = w ? S2 : S0;
            S2: next_state = w ? S2 : S3;
            S3: next_state = w ? S4 : S0;
            S4: next_state = w ? S2 : S0;
            default: next_state = S0;
        endcase
    end
    always @(*) z = (state == S4);
endmodule

projects/vlsi-hardware-arbiters/part2_tb.v
`timescale 1ns/1ps

module part2_tb;

    reg clk;
    reg rst_n;
    reg button;
    reg w_5, w_6, x_6, w_7;
    
    wire pulse_rise;
    wire pulse_fall;
    wire z_5;
    wire z_6;
    wire z_7;

    rising_edge_det u_rise (.clk(clk), .button(button), .pulse(pulse_rise));
    falling_edge_det u_fall (.clk(clk), .button(button), .pulse(pulse_fall));
    fsm_w u_fsm_w (.clk(clk), .rst_n(rst_n), .w(w_5), .z(z_5));
    fsm_wx u_fsm_wx (.clk(clk), .rst_n(rst_n), .w(w_6), .x(x_6), .z(z_6));
    fsm_1101 u_fsm_1101 (.clk(clk), .rst_n(rst_n), .w(w_7), .z(z_7));

    initial begin
        clk = 0;
        forever #5 clk = ~clk;
    end

    initial begin
        $dumpfile("part2.vcd");
        $dumpvars(0, part2_tb);

        rst_n = 0;
        button = 0;
        w_5 = 0; w_6 = 0; x_6 = 0; w_7 = 0;
        #12;
        rst_n = 1;

        $display("--- Testing Edge Detectors ---");
        @(negedge clk) button = 1;
        @(negedge clk) button = 1;
        @(negedge clk) button = 0;
        @(negedge clk) button = 0;

        $display("--- Testing FSM 5 (w=1 for two preceding cycles) ---");
        // w: 0 1 0 1 1 0 1 1 1 0 1
        @(negedge clk) w_5 = 0;
        @(negedge clk) w_5 = 1;
        @(negedge clk) w_5 = 0;
        @(negedge clk) w_5 = 1;
        @(negedge clk) w_5 = 1;
        @(negedge clk) w_5 = 0;
        @(negedge clk) w_5 = 1;
        @(negedge clk) w_5 = 1;
        @(negedge clk) w_5 = 1;
        @(negedge clk) w_5 = 0;
        @(negedge clk) w_5 = 1;

        $display("--- Testing FSM 6 (w!=x for three cycles) ---");
        @(negedge clk) w_6 = 0; x_6 = 1; // 1 cycle
        @(negedge clk) w_6 = 1; x_6 = 0; // 2 cycles
        @(negedge clk) w_6 = 0; x_6 = 1; // 3 cycles -> z=1
        @(negedge clk) w_6 = 1; x_6 = 1; // 0 cycles
        @(negedge clk) w_6 = 0; x_6 = 1; // 1 cycle
        
        $display("--- Testing FSM 7 (1101) ---");
        @(negedge clk) w_7 = 1;
        @(negedge clk) w_7 = 1;
        @(negedge clk) w_7 = 0;
        @(negedge clk) w_7 = 1; // Sequence 1101 complete -> z=1
        @(negedge clk) w_7 = 1; // Sequence is now 11011 (suffix 11)
        @(negedge clk) w_7 = 0; // Suffix 110
        @(negedge clk) w_7 = 1; // Sequence 1101 again -> z=1

        @(negedge clk);
        @(negedge clk);
        $finish;
    end

    always @(posedge clk) begin
        #1;
        $display("Time=%0t | btn=%b rise=%b fall=%b | w5=%b z5=%b | w6=%b x6=%b z6=%b | w7=%b z7=%b",
            $time, button, pulse_rise, pulse_fall, w_5, z_5, w_6, x_6, z_6, w_7, z_7);
    end

endmodule

projects/vlsi-hardware-arbiters/part2.vcd
$date
	Wed Jun 10 01:49:46 2026
$end
$version
	Icarus Verilog
$end
$timescale
	1ps
$end
$scope module part2_tb $end
$var wire 1 ! z_7 $end
$var wire 1 " z_6 $end
$var wire 1 # z_5 $end
$var wire 1 $ pulse_rise $end
$var wire 1 % pulse_fall $end
$var reg 1 & button $end
$var reg 1 ' clk $end
$var reg 1 ( rst_n $end
$var reg 1 ) w_5 $end
$var reg 1 * w_6 $end
$var reg 1 + w_7 $end
$var reg 1 , x_6 $end
$scope module u_fall $end
$var wire 1 & button $end
$var wire 1 ' clk $end
$var wire 1 % pulse $end
$var reg 1 - button_d $end
$var reg 1 . button_dd $end
$upscope $end
$scope module u_fsm_1101 $end
$var wire 1 ' clk $end
$var wire 1 ( rst_n $end
$var wire 1 + w $end
$var parameter 3 / S0 $end
$var parameter 3 0 S1 $end
$var parameter 3 1 S2 $end
$var parameter 3 2 S3 $end
$var parameter 3 3 S4 $end
$var reg 3 4 next_state [2:0] $end
$var reg 3 5 state [2:0] $end
$var reg 1 ! z $end
$upscope $end
$scope module u_fsm_w $end
$var wire 1 ' clk $end
$var wire 1 ( rst_n $end
$var wire 1 ) w $end
$var parameter 2 6 S0 $end
$var parameter 2 7 S1 $end
$var parameter 2 8 S2 $end
$var reg 2 9 next_state [1:0] $end
$var reg 2 : state [1:0] $end
$var reg 1 # z $end
$upscope $end
$scope module u_fsm_wx $end
$var wire 1 ' clk $end
$var wire 1 ; diff $end
$var wire 1 ( rst_n $end
$var wire 1 * w $end
$var wire 1 , x $end
$var parameter 2 < S0 $end
$var parameter 2 = S1 $end
$var parameter 2 > S2 $end
$var parameter 2 ? S3 $end
$var reg 2 @ next_state [1:0] $end
$var reg 2 A state [1:0] $end
$var reg 1 " z $end
$upscope $end
$scope module u_rise $end
$var wire 1 & button $end
$var wire 1 ' clk $end
$var wire 1 $ pulse $end
$var reg 1 B button_d $end
$var reg 1 C button_dd $end
$upscope $end
$upscope $end
$enddefinitions $end
$comment Show the parameter values. $end
$dumpall
b11 ?
b10 >
b1 =
b0 <
b10 8
b1 7
b0 6
b100 3
b11 2
b10 1
b1 0
b0 /
$end
#0
$dumpvars
xC
xB
b0 A
b0 @
0;
b0 :
b0 9
b0 5
b0 4
x.
x-
0,
0+
0*
0)
0(
0'
0&
x%
x$
0#
0"
0!
$end
#5000
0$
0B
0-
1'
#10000
0'
#12000
1(
#15000
0%
0.
0C
1'
#20000
1&
0'
#25000
1$
1B
1-
1'
#30000
0'
#35000
0$
1.
1C
1'
#40000
0&
0'
#45000
1%
0B
0-
1'
#50000
0'
#55000
0%
0.
0C
1'
#60000
0'
#65000
1'
#70000
b1 9
1)
0'
#75000
b10 9
b1 :
1'
#80000
b0 9
0)
0'
#85000
b0 :
1'
#90000
b1 9
1)
0'
#95000
b10 9
b1 :
1'
#100000
0'
#105000
1#
b10 :
1'
#110000
b0 9
0)
0'
#115000
0#
b0 :
1'
#120000
b1 9
1)
0'
#125000
b10 9
b1 :
1'
#130000
0'
#135000
1#
b10 :
1'
#140000
0'
#145000
1'
#150000
b0 9
0)
0'
#155000
0#
b0 :
1'
#160000
b1 9
1)
0'
#165000
b10 9
b1 :
1'
#170000
b1 @
1;
1,
0'
#175000
1#
b10 @
b10 :
b1 A
1'
#180000
0,
1*
0'
#185000
b11 @
b10 A
1'
#190000
1,
0*
0'
#195000
1"
b11 A
1'
#200000
b0 @
0;
1*
0'
#205000
0"
b0 A
1'
#210000
b1 @
1;
0*
0'
#215000
b10 @
b1 A
1'
#220000
b1 4
1+
0'
#225000
b10 4
b11 @
b1 5
b10 A
1'
#230000
0'
#235000
1"
b11 A
b10 5
1'
#240000
b11 4
0+
0'
#245000
b0 4
b11 5
1'
#250000
b100 4
1+
0'
#255000
1!
b10 4
b100 5
1'
#260000
0'
#265000
0!
b10 5
1'
#270000
b11 4
0+
0'
#275000
b0 4
b11 5
1'
#280000
b100 4
1+
0'
#285000
1!
b10 4
b100 5
1'
#290000
0'
#295000
0!
b10 5
1'
