projects/vlsi-hardware-arbiters/Archive/Smart_arb.v
module Smart_arb (
    input  wire       clk,
    input  wire       rst_n,
    input  wire [2:0] req,
    output reg  [2:0] gnt
);

    reg [1:0] last_one_gnt;
    reg [1:0] last_two_gnt;

    reg [1:0] score0, score1, score2;
    reg [1:0] winner;

    // Calculate scores based on history
    // 2 = not in history (highest priority)
    // 1 = in last_two_gnt but not last_one_gnt
    // 0 = in last_one_gnt (lowest priority)
    always @(*) begin
        score0 = (last_one_gnt == 2'd0) ? 2'd0 : ((last_two_gnt == 2'd0) ? 2'd1 : 2'd2);
        score1 = (last_one_gnt == 2'd1) ? 2'd0 : ((last_two_gnt == 2'd1) ? 2'd1 : 2'd2);
        score2 = (last_one_gnt == 2'd2) ? 2'd0 : ((last_two_gnt == 2'd2) ? 2'd1 : 2'd2);
    end

    // Determine the winner among active requesters
    always @(*) begin
        case (req)
            3'b000: winner = 2'd3; // No request
            3'b001: winner = 2'd0; // Only req[0]
            3'b010: winner = 2'd1; // Only req[1]
            3'b100: winner = 2'd2; // Only req[2]
            3'b011: begin // req[0] and req[1]
                if (score0 >= score1) winner = 2'd0;
                else                  winner = 2'd1;
            end
            3'b101: begin // req[0] and req[2]
                if (score0 >= score2) winner = 2'd0;
                else                  winner = 2'd2;
            end
            3'b110: begin // req[1] and req[2]
                if (score1 >= score2) winner = 2'd1;
                else                  winner = 2'd2;
            end
            3'b111: begin // All requests
                if (score0 >= score1 && score0 >= score2) winner = 2'd0;
                else if (score1 > score0 && score1 >= score2) winner = 2'd1;
                else winner = 2'd2;
            end
            default: winner = 2'd3;
        endcase
    end

    // Update state and output
    always @(posedge clk or negedge rst_n) begin
        if (!rst_n) begin
            // At reset, prefer lower number requester if no conflicts
            // So we set history such that 0 > 1 > 2
            last_one_gnt <= 2'd2;
            last_two_gnt <= 2'd1;
            gnt          <= 3'b000;
        end else begin
            if (winner != 2'd3) begin
                last_two_gnt <= last_one_gnt;
                last_one_gnt <= winner;
                
                if (winner == 2'd0)      gnt <= 3'b001;
                else if (winner == 2'd1) gnt <= 3'b010;
                else if (winner == 2'd2) gnt <= 3'b100;
            end else begin
                gnt <= 3'b000;
                // last_one_gnt and last_two_gnt remain unchanged when no requests are given
            end
        end
    end

endmodule

projects/vlsi-hardware-arbiters/smart_arb_tb.v
`timescale 1ns/1ps

module smart_arb_tb;

    reg clk;
    reg rst_n;
    reg [2:0] req;
    wire [2:0] gnt;

    // Instantiate the smart arbiter
    Smart_arb uut (
        .clk(clk),
        .rst_n(rst_n),
        .req(req),
        .gnt(gnt)
    );

    // Clock generation
    initial begin
        clk = 0;
        forever #5 clk = ~clk;
    end

    // Stimulus
    initial begin
        $dumpfile("smart_arb.vcd");
        $dumpvars(0, smart_arb_tb);

        // Initialize inputs
        rst_n = 0;
        req = 3'b000;
        
        // Wait for reset
        #12;
        rst_n = 1;

        // Apply scenarios to test history and fairness
        
        // Test 1: req 0 gets grant twice
        @(negedge clk) req = 3'b001; 
        @(negedge clk) req = 3'b001; 

        // Test 2: all requests asserted. Since 0 just got it twice, it should prefer lower number between 1 and 2, which is 1
        @(negedge clk) req = 3'b111; 
        
        // Test 3: all requests asserted again. Now history is (0, 1), so 2 should win
        @(negedge clk) req = 3'b111; 
        
        // Test 4: all requests asserted again. History is (1, 2), so 0 should win
        @(negedge clk) req = 3'b111; 

        // Test 5: req 1 and 2. History is (2, 0). 1 is not in history, so 1 should win
        @(negedge clk) req = 3'b110; 

        // Test 6: No requests. gnt should be 000 and history unchanged.
        @(negedge clk) req = 3'b000; 

        // Test 7: req 0 and 2. History is still (0, 1) from before req=000? 
        // Wait, after req=110, history became (0, 1). 
        // Let's see what happens here!
        @(negedge clk) req = 3'b101; 

        // Additional cycles to observe the output
        @(negedge clk);
        @(negedge clk);
        
        $finish;
    end

    // Clear printouts of grants and history at each clock cycle
    always @(posedge clk) begin
        // delay by a small amount to allow state and gnt to update
        #1;
        $display("Time=%0t | req=%b | gnt=%b | last_one=%0d | last_two=%0d", 
                 $time, req, gnt, uut.last_one_gnt, uut.last_two_gnt);
    end

endmodule

projects/vlsi-hardware-arbiters/smart_arb.vcd
$date
	Wed Jun 10 01:49:46 2026
$end
$version
	Icarus Verilog
$end
$timescale
	1ps
$end
$scope module smart_arb_tb $end
$var wire 3 ! gnt [2:0] $end
$var reg 1 " clk $end
$var reg 3 # req [2:0] $end
$var reg 1 $ rst_n $end
$scope module uut $end
$var wire 1 " clk $end
$var wire 3 % req [2:0] $end
$var wire 1 $ rst_n $end
$var reg 3 & gnt [2:0] $end
$var reg 2 ' last_one_gnt [1:0] $end
$var reg 2 ( last_two_gnt [1:0] $end
$var reg 2 ) score0 [1:0] $end
$var reg 2 * score1 [1:0] $end
$var reg 2 + score2 [1:0] $end
$var reg 2 , winner [1:0] $end
$upscope $end
$upscope $end
$enddefinitions $end
$comment Show the parameter values. $end
$dumpall
$end
#0
$dumpvars
b11 ,
b0 +
b1 *
b10 )
b1 (
b10 '
b0 &
b0 %
0$
b0 #
0"
b0 !
$end
#5000
1"
#10000
0"
#12000
1$
#15000
1"
#20000
b0 ,
b1 #
b1 %
0"
#25000
b1 +
b10 *
b0 )
b1 !
b1 &
b0 '
b10 (
1"
#30000
0"
#35000
b10 +
b0 (
1"
#40000
b1 ,
b111 #
b111 %
0"
#45000
b10 ,
b0 *
b1 )
b10 !
b10 &
b1 '
1"
#50000
0"
#55000
b0 ,
b0 +
b1 *
b10 )
b100 !
b100 &
b10 '
b1 (
1"
#60000
0"
#65000
b1 ,
b1 +
b10 *
b0 )
b1 !
b1 &
b0 '
b10 (
1"
#70000
b110 #
b110 %
0"
#75000
b10 ,
b10 +
b0 *
b1 )
b10 !
b10 &
b1 '
b0 (
1"
#80000
b11 ,
b0 #
b0 %
0"
#85000
b0 !
b0 &
1"
#90000
b10 ,
b101 #
b101 %
0"
#95000
b0 ,
b0 +
b1 *
b10 )
b100 !
b100 &
b10 '
b1 (
1"
#100000
0"
#105000
b10 ,
b1 +
b10 *
b0 )
b1 !
b1 &
b0 '
b10 (
1"
